Workbook

Sheet DCF
B2: Discounted Cash Flow Valuation
B3: $ and shares in millions, except per share data
B4: Most recent fiscal year end | D4: 46022 | F4: Discount rate (WACC) | H4: =WACC!E21 -> 0.09531164
B5: End of first fiscal year | D5: =EOMONTH(D4,12) -> 46387 | F5: Share price | H5: 198.79
B6: Most recent quarter end date | D6: 46022 | F6: Share price date | H6: 46066
B7: Valuation date | D7: 46066 | F7: Midyear adjustment? | H7: 0
B8: Portion of First Year Cash Flows | D8: =YEARFRAC(D7,D5) -> 0.88333333
F9: Case active: | H9: ='3 Statement Model'!C12 -> Base case
B10: Unlevered Free Cash Flows
C11: LTM | D11: Actual | E11: Forecasts
B12: Fiscal year ended | C12: =D7 -> 46066 | D12: =D4 -> 46022 | E12: =EOMONTH(D12,12) -> 46387 | F12: =EOMONTH(E12,12) -> 46752 | G12: =EOMONTH(F12,12) -> 47118 | H12: =EOMONTH(G12,12) -> 47483 | I12: =EOMONTH(H12,12) -> 47848
B14: Revenue | C14: =+E14*(1-$D$8)+D14*$D$8 -> 727206.12 | D14: ='3 Statement Model'!E18 -> 716924 | E14: ='3 Statement Model'!F18 -> 805056.43 | F14: ='3 Statement Model'!G18 -> 895555.18 | G14: ='3 Statement Model'!H18 -> 1009191.8 | H14: ='3 Statement Model'!I18 -> 1137247.8 | I14: ='3 Statement Model'!J18 -> 1281552.7
B15: % growth | E15: =E14/D14-1 -> 0.12293134 | F15: =F14/E14-1 -> 0.11241293 | G15: =G14/F14-1 -> 0.1268896 | H15: =H14/G14-1 -> 0.1268896 | I15: =I14/H14-1 -> 0.1268896
B16: EBITDA | C16: =+E16*(1-$D$8)+D16*$D$8 -> 150534.35 | D16: ='3 Statement Model'!E34 -> 145731 | E16: ='3 Statement Model'!F34 -> 186902.6 | F16: ='3 Statement Model'!G34 -> 209981.59 | G16: ='3 Statement Model'!H34 -> 254753.1 | H16: ='3 Statement Model'!I34 -> 291579.09 | I16: ='3 Statement Model'!J34 -> 333636.68
B17: % margin | D17: =D16/D14 -> 0.20327259 | E17: =E16/E14 -> 0.23216087 | F17: =F16/F14 -> 0.23447086 | G17: =G16/G14 -> 0.25243279 | H17: =H16/H14 -> 0.25639012 | I17: =I16/I14 -> 0.26033786
B18: EBIT | C18: =+E18*(1-$D$8)+D18*$D$8 -> 82301.023 | D18: ='3 Statement Model'!E24 -> 79975 | E18: ='3 Statement Model'!F24 -> 99912.342 | F18: ='3 Statement Model'!G24 -> 115972.81 | G18: ='3 Statement Model'!H24 -> 147341.86 | H18: ='3 Statement Model'!I24 -> 166134.82 | I18: ='3 Statement Model'!J24 -> 187312.42
B19: % margin | D19: =D18/D14 -> 0.11155297 | E19: =E18/E14 -> 0.12410601 | F19: =F18/F14 -> 0.12949823 | G19: =G18/G14 -> 0.14599985 | H19: =H18/H14 -> 0.14608499 | I19: =I18/I14 -> 0.14616053
B21: Tax on EBIT | D21: =D22*D18 -> 15686.642 | E21: =E22*E18 -> 18523.748 | F21: =F22*F18 -> 21744.902 | G21: =G22*G18 -> 27405.585 | H21: =H22*H18 -> 30901.077 | I21: =I22*I18 -> 34840.11
B22: Tax rate | D22: ='3 Statement Model'!E43 -> 0.19614432 | E22: ='3 Statement Model'!F43 -> 0.1854 | F22: ='3 Statement Model'!G43 -> 0.1875 | G22: ='3 Statement Model'!H43 -> 0.186 | H22: ='3 Statement Model'!I43 -> 0.186 | I22: ='3 Statement Model'!J43 -> 0.186
B23: NOPAT | D23: =D18*(1-D22) -> 64288.358 | E23: =E18*(1-E22) -> 81388.594 | F23: =F18*(1-F22) -> 94227.91 | G23: =G18*(1-G22) -> 119936.27 | H23: =H18*(1-H22) -> 135233.75 | I23: =I18*(1-I22) -> 152472.31
B25: Depreciation & amortization | D25: ='3 Statement Model'!E33 -> 65756 | E25: ='3 Statement Model'!F33 -> 86990.258 | F25: ='3 Statement Model'!G33 -> 94008.777 | G25: ='3 Statement Model'!H33 -> 107411.25 | H25: ='3 Statement Model'!I33 -> 125444.27 | I25: ='3 Statement Model'!J33 -> 146324.26
B26: Changes in net working capital | E26: =D32-E32 -> 13721.087 | F26: =E32-F32 -> 12679.898 | G26: =F32-G32 -> 15743.302 | H26: =G32-H32 -> 19553.089 | I26: =H32-I32 -> 22034.173
B27: Capital expenditures | E27: ='3 Statement Model'!F85 -> -178185.02 | F27: ='3 Statement Model'!G85 -> -179424.13 | G27: ='3 Statement Model'!H85 -> -195389.49 | H27: ='3 Statement Model'!I85 -> -220182.38 | I27: ='3 Statement Model'!J85 -> -248121.24
B28: as % of revenue | E28: =E27/E14 -> -0.22133234 | F28: =F27/F14 -> -0.20034961 | G28: =G27/G14 -> -0.19360986 | H28: =H27/H14 -> -0.19360986 | I28: =I27/I14 -> -0.19360986
B30: Unlevered free cash flows (UFCF) | E30: =E23+E25+E26+E27 -> 3914.9193 | F30: =F23+F25+F26+F27 -> 21492.454 | G30: =G23+G25+G26+G27 -> 47701.331 | H30: =H23+H25+H26+H27 -> 60048.717 | I30: =I23+I25+I26+I27 -> 72709.508
B32: Net working capital (WC Assets - WC liabilities) | D32: =SUM('3 Statement Model'!E49,'3 Statement Model'!E50)-SUM('3 Statement Model'!E55,'3 Statement Model'!E56,'3 Statement Model'!E57) -> -111951 | E32: =SUM('3 Statement Model'!F49,'3 Statement Model'!F50)-SUM('3 Statement Model'!F55,'3 Statement Model'!F56,'3 Statement Model'!F57) -> -125672.09 | F32: =SUM('3 Statement Model'!G49,'3 Statement Model'!G50)-SUM('3 Statement Model'!G55,'3 Statement Model'!G56,'3 Statement Model'!G57) -> -138351.99 | G32: =SUM('3 Statement Model'!H49,'3 Statement Model'!H50)-SUM('3 Statement Model'!H55,'3 Statement Model'!H56,'3 Statement Model'!H57) -> -154095.29 | H32: =SUM('3 Statement Model'!I49,'3 Statement Model'!I50)-SUM('3 Statement Model'!I55,'3 Statement Model'!I56,'3 Statement Model'!I57) -> -173648.38 | I32: =SUM('3 Statement Model'!J49,'3 Statement Model'!J50)-SUM('3 Statement Model'!J55,'3 Statement Model'!J56,'3 Statement Model'!J57) -> -195682.55
B33: as % of revenue | D33: =D32/D14 -> -0.15615463 | E33: =E32/E14 -> -0.15610345 | F33: =F32/F14 -> -0.15448739 | G33: =G32/G14 -> -0.15269177 | H33: =H32/H14 -> -0.15269177 | I33: =I32/I14 -> -0.15269177
B35: ="Present value of UFCF on "&TEXT(D7,"mmm dd, yyyy")&" valuation date" -> Present value of UFCF on Feb 13, 2026 valuation date
D36: Val date | E36: Yr 1 - Stub | F36: Year 2 | G36: Year 3 | H36: Year 4 | I36: Year 5
B37: Date for discounting cash flows | D37: =D7 -> 46066 | E37: =IF($H$7=1,AVERAGE(E12,D37),E12) -> 46387 | F37: =IF($H$7=1,AVERAGE(F12,E12),F12) -> 46752 | G37: =IF($H$7=1,AVERAGE(G12,F12),G12) -> 47118 | H37: =IF($H$7=1,AVERAGE(H12,G12),H12) -> 47483 | I37: =IF($H$7=1,AVERAGE(I12,H12),I12) -> 47848
B38: Unlevered free cash flows (UFCF) stub adjusted | C38: =D8 -> 0.88333333 | E38: =E30*C38 -> 3458.1788 | F38: =F30 -> 21492.454 | G38: =G30 -> 47701.331 | H38: =H30 -> 60048.717 | I38: =I30 -> 72709.508
B39: Present value of of unlevered free cash flows | E39: =E38/(1+$H$4)^((E37-$D$7)/365) -> 3192.0959 | F39: =F38/(1+$H$4)^((F37-$D$7)/365) -> 18112.433 | G39: =G38/(1+$H$4)^((G37-$D$7)/365) -> 36692.327 | H39: =H38/(1+$H$4)^((H37-$D$7)/365) -> 42170.698 | I39: =I38/(1+$H$4)^((I37-$D$7)/365) -> 46618.743
B41: Terminal value - growth in perpetuity approach | E41: Terminal value - EBITDA multiple approach
B42: Long term growth rate | C42: 0.023 | E42: Terminal year EBITDA | I42: =I16 -> 333636.68
B43: =YEAR(I12)&" FCF x (1+g)" -> 2030 FCF x (1+g) | C43: =I38*(1+C42) -> 74381.827 | E43: EBITDA multiple | I43: 10.3
B44: ="Terminal value in "&YEAR(I12) -> Terminal value in 2030 | C44: =C43/(H4-C42) -> 1028628.7 | E44: ="Terminal value in "&YEAR(I12) -> Terminal value in 2030 | I44: =I42*I43 -> 3436457.8
B45: Present value of terminal value | C45: =C44/(1+H4)^((I37-$D$37)/365) -> 659520.02 | E45: Present value of terminal value | I45: =I44/(1+H4)^((I37-D37)/365) -> 2203334.2
B46: Present value of stage 1 cash flows | C46: =SUM(E39:I39) -> 146786.3 | E46: Present value of stage 1 cash flows | I46: =C46 -> 146786.3
B47: Total enterprise value (TEV) | C47: =C46+C45 -> 806306.32 | E47: Enterprise value (stage 1 + 2) | I47: =SUM(I45:I46) -> 2350120.5
B49: Terminal value as % of TEV | C49: =C45/$C$47 -> 0.81795219 | E49: Terminal value as % of TEV | I49: =+I45/I47 -> 0.93754095
B50: Stage 1 cash flows as % of TEV | C50: =1-C49 -> 0.18204781 | E50: Cash flows as % of TEV | I50: =1-I49 -> 0.062459052
B51: Implied TV exit EBITDA multiple | C51: =(C44/I16) -> 3.0830803 | E51: Implied terminal growth rate | I51: =(H4-I38/I44)/(1+I38/I44) -> 0.07261692
B53: Net debt | E53: Shares outstanding
B54: Source doc | C54: FY 2026
B55: Source date | C55: =D6 -> 46022 | G55: Source doc | H55: Date | I55: Shares
B56: Gross debt and equivalents | E56: Basic shares | G56: FY 2026 | H56: ='3 Statement Model'!C10 -> 46022 | I56: ='3 Statement Model'!C11 -> 10734.921
B57: Debt | C57: ='3 Statement Model'!E59 -> 65648 | E57: Restricted stock / RSUs | G57: FY 2026 | H57: ='3 Statement Model'!C10 -> 46022 | I57: 222.5
B58: Convertible debt | C58: 0 | E58: Options / warrants | I58: 0
B59: Preferred stock | C59: 0 | E59: Convertible debt | I59: 0
B60: Noncontrolling (minority) interests | C60: 0 | E60: Convertible preferred stock | I60: 0
B61: Nonoperating assets | E61: Net diluted shares outstanding | I61: =SUM(I56:I60) -> 10957.421
B62: Cash | C62: ='3 Statement Model'!E48 -> 123029
B63: Equity investments | C63: 0
B65: Net debt | C65: =SUM(C57:C60)-SUM(C62:C63) -> -57381
B67: Valuation
C68: Perpetuity | D68: EBITDA
B69: Enterprise value | C69: =C47 -> 806306.32 | D69: =I47 -> 2350120.5
B70: Net debt | C70: =$C$65 -> -57381 | D70: =C70 -> -57381
B71: Equity value | C71: =C69-C70 -> 863687.32 | D71: =D69-D70 -> 2407501.5
B72: Shares outstanding | C72: =$I$61 -> 10957.421 | D72: =C72 -> 10957.421
B73: Equity value per share | C73: =C71/C72 -> 78.822136 | D73: =D71/D72 -> 219.71425
C75: Last twelve months (LTM)
C76: Perpetuity | D76: EBITDA
B77: EV / Revenue | C77: =C69/$C$14 -> 1.1087727 | D77: =D69/$C$14 -> 3.2317117
B78: EV / EBITDA | C78: =C69/$C$16 -> 5.3562944 | D78: =D69/$C$16 -> 15.611855
B79: EV / EBIT | C79: =C69/$C$18 -> 9.7970388 | D79: =D69/$C$18 -> 28.555179
C80: Year 1
C81: Perpetuity | D81: EBITDA
B82: EV / Revenue | C82: =C69/$E$14 -> 1.0015525 | D82: =D69/$E$14 -> 2.9191997
B83: EV / EBITDA | C83: =C69/$E$16 -> 4.3140455 | D83: =D69/$E$16 -> 12.574038
B84: EV / EBIT | C84: =C69/$E$18 -> 8.0701373 | D84: =D69/$E$18 -> 23.521824
B86: Outputs
D88: Equity value per share | L88: LTM EBITDA multiple
E89: Long term growth rate (g): | M89: Long term growth rate (g):
D90: =C73 -> 78.822136 | E90: =F90-0.005 -> 0.013 | F90: =G90-0.005 -> 0.018 | G90: 0.023 | H90: =G90+0.005 -> 0.028 | I90: =H90+0.005 -> 0.033 | L90: =C78 -> 5.3562944 | M90: =N90-0.005 -> 0.013 | N90: =O90-0.005 -> 0.018 | O90: 0.023 | P90: =O90+0.005 -> 0.028 | Q90: =P90+0.005 -> 0.033
D91: =D92+0.01 -> 0.11531164 | E91: 56.344846 | F91: 58.526379 | G91: 60.944234 | H91: 63.639012 | I91: 66.661177 | L91: =L92+0.01 -> 0.11531164 | M91: 3.7201687 | N91: 3.8789628 | O91: 4.0549589 | P91: 4.2511123 | Q91: 4.4710962
D92: =D93+0.01 -> 0.10531164 | E92: 62.859495 | F92: 65.650163 | G92: 68.779868 | H92: 72.314389 | I92: 76.337701 | L92: =L93+0.01 -> 0.10531164 | M92: 4.1943711 | N92: 4.3975043 | O92: 4.625316 | P92: 4.8825944 | Q92: 5.175452
C93: WACC: | D93: 0.09531164 | E93: 70.992881 | F93: 74.654336 | G93: 78.822136 | H93: 83.609115 | I93: 89.164326 | K93: WACC: | L93: 0.09531164 | M93: 4.7864016 | N93: 5.0529196 | O93: 5.3562944 | P93: 5.7047394 | Q93: 6.1091042
D94: =D93-0.01 -> 0.08531164 | E94: 81.418403 | F94: 86.378901 | G94: 92.135477 | H94: 98.896488 | I94: 106.94995 | L94: =L93-0.01 -> 0.08531164 | M94: 5.5452772 | N94: 5.9063526 | O94: 6.3253748 | P94: 6.8175099 | Q94: 7.4037225
B95: Data | D95: =D94-0.01 -> 0.07531164 | E95: 95.241865 | F95: 102.25026 | G95: 110.59839 | H95: 120.71102 | I95: 133.21369 | L95: =L94-0.01 -> 0.07531164 | M95: 6.5514892 | N95: 7.0616314 | O95: 7.6692933 | P95: 8.4053934 | Q95: 9.3154646
B96: Tables
D97: Equity value per share | L97: LTM EBITDA multiple
E98: Exit EBITDA Multiple | M98: Exit EBITDA Multiple
D99: =D73 -> 219.71425 | E99: =F99-1 -> 9 | F99: =G99-1 -> 10 | G99: 11 | H99: =G99+1 -> 12 | I99: =H99+1 -> 13 | L99: =D78 -> 15.611855 | M99: =N99-1 -> 9 | N99: =O99-1 -> 10 | O99: 11 | P99: =O99+1 -> 12 | Q99: =P99+1 -> 13
D100: =D101+0.01 -> 0.11531164 | E100: 178.62801 | F100: 196.4998 | G100: 214.37158 | H100: 232.24337 | I100: 250.11515 | L100: =L101+0.01 -> 0.11531164 | M100: 12.621181 | N100: 13.922071 | O100: 15.222961 | P100: 16.523852 | Q100: 17.824742
D101: =D102+0.01 -> 0.10531164 | E101: 186.27436 | F101: 204.94954 | G101: 223.62471 | H101: 242.29988 | I101: 260.97505 | L101: =L102+0.01 -> 0.10531164 | M101: 13.17776 | N101: 14.537129 | O101: 15.896498 | P101: 17.255867 | Q101: 18.615236
C102: WACC: | D102: 0.09531164 | E102: 194.33503 | F102: 213.85751 | G102: 233.37998 | H102: 252.90245 | I102: 272.42492 | K102: WACC: | L102: 0.09531164 | M102: 13.764498 | N102: 15.185542 | O102: 16.606586 | P102: 18.02763 | Q102: 19.448674
D103: =D102-0.01 -> 0.08531164 | E103: 202.83663 | F103: 223.25315 | G103: 243.66967 | H103: 264.0862 | I103: 284.50272 | L103: =L102-0.01 -> 0.08531164 | M103: 14.38333 | N103: 15.869452 | O103: 17.355574 | P103: 18.841696 | Q103: 20.327818
D104: =D103-0.01 -> 0.07531164 | E104: 211.80774 | F104: 233.16811 | G104: 254.52847 | H104: 275.88884 | I104: 297.24921 | L104: =L103-0.01 -> 0.07531164 | M104: 15.036339 | N104: 16.591164 | O104: 18.145988 | P104: 19.700813 | Q104: 21.255638
B106: Equity value range | G106: Football field
C127: Low | D127: Diff. | E127: High | O127: Low | P127: Diff. | Q127: High
B128: ="DCF Value at "&TEXT(E99,"0.0x")&"-"&TEXT(I99,"0.0x")&" Exit EBITDA Range at "&TEXT(D102,"0.0%")&" WACC" -> DCF Value at 9.0x-13.0x Exit EBITDA Range at 9.5% WACC | C128: =E102 -> 194.33503 | D128: =E128-C128 -> 78.089887 | E128: =I102 -> 272.42492 | G128: ="LTM EBITDA Purchase Multiple at "&TEXT(M90,"0.0%")&"-"&TEXT(Q90,"0.0%")&" Perpetuity Growth at "&TEXT(L93,"0.0%")&" WACC" -> LTM EBITDA Purchase Multiple at 1.3%-3.3% Perpetuity Growth at 9.5% WACC | O128: =M93 -> 4.7864016 | P128: =Q128-O128 -> 1.3227026 | Q128: =Q93 -> 6.1091042
B129: ="DCF Value at "&TEXT(E90,"0.0%")&"-"&TEXT(I90,"0.0%")&" Perpetuity Range at "&TEXT(D102,"0.0%")&" WACC" -> DCF Value at 1.3%-3.3% Perpetuity Range at 9.5% WACC | C129: =E93 -> 70.992881 | D129: =E129-C129 -> 18.171446 | E129: =I93 -> 89.164326 | G129: ="LTM EBITDA Purchase Multiple at "&TEXT(M102,"0.0x")&"-"&TEXT(Q102,"0.0x")&" Exit EBITDA Multiple at "&TEXT(L102,"0.0%")&" WACC" -> LTM EBITDA Purchase Multiple at 13.8x-19.4x Exit EBITDA Multiple at 9.5% WACC | O129: =M102 -> 13.764498 | P129: =Q129-O129 -> 5.684176 | Q129: =Q102 -> 19.448674
B130: 52 Week Market High/Low | C130: 161.38 | D130: =E130-C130 -> 97.22 | E130: 258.6 | G130: ="LTM EBITDA Purchase Multiple at "&TEXT(L104,"0.0%")&"-"&TEXT(L100,"0.0%")&" WACC at "&TEXT(O99,"0.0x")&" Exit EBITDA" -> LTM EBITDA Purchase Multiple at 7.5%-11.5% WACC at 11.0x Exit EBITDA | O130: =O100 -> 15.222961 | P130: =Q130-O130 -> 2.923027 | Q130: =O104 -> 18.145988

Sheet WACC
B2: WACC Buildup
B3: $ and shares in millions, except per share data
B4: Cost of capital assumptions
E5: Source
B6: Cost of debt | C6: 0.03988 | E6: Capital IQ - YTM on 4.1% 11/30
B7: Tax rate | C7: ='3 Statement Model'!J43 -> 0.186 | E7: From terminal year of UFCF forecast
B8: Cost of debt (after tax) | C8: =C6*(1-C7) -> 0.03246232 | E8: Cost of debt x (1 - tax rate)
B10: Risk free rate | C10: 0.03611 | E10: WSJ: 5 Year US Treasury Yield
B11: Beta | C11: =IF(C32="Observed",C34,C35) -> 1.38 | E11: Bloomberg 2 year weekly adjusted beta
B12: Market risk premium | C12: 0.0417 | E12: Damodaran implied ERP 2/26
B13: Cost of equity | C13: =C10+C11*C12 -> 0.093656 | E13: RfR + Beta x MRP
B15: Capital weights (capital structure)
D16: Target
C17: Current | D17: (override) | E17: % of total
B18: Equity | C18: =DCF!I61*DCF!H5 -> 2178225.7 | E18: =IF(D18,D18,C18/(C18+C19)) -> 1.0270557
B19: Debt | C19: ='3 Statement Model'!E59-'3 Statement Model'!E48 -> -57381 | D19: =1-D18 -> 1 | E19: =1-E18 -> -0.027055729
B21: Cost of capital (WACC) | E21: =C8*E19+C13*E18 -> 0.09531164
B23: WACC sensitivity to MRP and Beta
D24: Beta
C25: =E21 -> 0.09531164 | D25: =E25-0.1 -> 1.28 | E25: 1.38 | F25: =E25+0.1 -> 1.48
C26: =C27-0.005 -> 0.0317 | D26: 0.061013495 | E26: 0.065908826 | F26: 0.070804156
B27: Market | C27: =C28-0.005 -> 0.0367 | D27: 0.066447312 | E27: 0.071886568 | F27: 0.077325824
B28: Risk | C28: 0.0417 | D28: 0.071881129 | E28: 0.077864311 | F28: 0.083847492
B29: Premium | C29: =C28+0.005 -> 0.0467 | D29: 0.077314946 | E29: 0.083842053 | F29: 0.090369161
C30: =C29+0.005 -> 0.0517 | D30: 0.082748763 | E30: 0.089819796 | F30: 0.096890829
B32: Select Beta for model | C32: Observed
B34: Observed | C34: 1.38 | D34: Bloomberg 2 year weekly adjusted beta
B35: Industry beta | C35: =C46 -> 1.0430125 | D35: From schedule below
B37: Industry beta
C39: Observed b | D39: Share price | E39: Dil. shares | F39: Market cap | G39: Net Debt | H39: Tax rate | I39: Delev. b
B40: Microsoft MSFT | C40: 1.08 | D40: 401.32 | E40: 7425.6 | F40: =D40*E40 -> 2980041.8 | G40: =40262-89462 -> -49200 | H40: 0.1763 | I40: =C40/(1+(1-H40)*(G40)/F40) -> 1.0948896
B41: Alphabet (GOOG) | C41: 1.09 | D41: 305.72 | E41: 12390 | F41: =D41*E41 -> 3787870.8 | G41: =23602-98496 -> -74894 | H41: 0.1678 | I41: =C41/(1+(1-H41)*(G41)/F41) -> 1.1082352
B42: Walmart (WMT) | C42: 0.67 | D42: 133.89 | E42: 7991.1 | F42: =D42*E42 -> 1069928.4 | G42: =53433-10582 -> 42851 | H42: 0.236 | I42: =C42/(1+(1-H42)*(G42)/F42) -> 0.6501077
B43: Amazon (AMZN) | C43: =C34 -> 1.38 | F43: =C18 -> 2178225.7 | G43: =C19 -> -57381 | H43: =C7 -> 0.186 | I43: =C43/(1+(1-H43)*(G43)/F43) -> 1.4102401
B45: Industry average delevered beta | C45: =AVERAGE(I40:I43) -> 1.0658681
B46: =B43&" beta" -> Amazon (AMZN) beta | C46: =C45*(1+(1-H43)*(G43)/F43) -> 1.0430125

Sheet 3 Statement Model
B2: ="Financial Statement Model for "&C5 -> Financial Statement Model for Amazon
B3: $ and shares in millions, except per share data
B5: Company name | C5: Amazon
B6: Ticker | C6: AMZN
B7: Circ break 1=off, 0=on | C7: 1
B8: Latest closing share price | C8: 198.79
B9: Latest closing share price date | C9: 46066
B10: Latest fiscal year end date | C10: 46022
B11: Shares outstanding (millions) | C11: 10734.921
B12: Select an operating scenario: | C12: Base case
B14: INCOME STATEMENT
B15: Fiscal year | C15: =D15-1 -> 2023 | D15: =E15-1 -> 2024 | E15: =YEAR(C10) -> 2025 | F15: =E15+1 -> 2026 | G15: =F15+1 -> 2027 | H15: =G15+1 -> 2028 | I15: =H15+1 -> 2029 | J15: =I15+1 -> 2030
B16: Fiscal year end date | C16: =EOMONTH(D16,-12) -> 45291 | D16: =EOMONTH(E16,-12) -> 45657 | E16: =C10 -> 46022 | F16: =EOMONTH(E16,12) -> 46387 | G16: =EOMONTH(F16,12) -> 46752 | H16: =EOMONTH(G16,12) -> 47118 | I16: =EOMONTH(H16,12) -> 47483 | J16: =EOMONTH(I16,12) -> 47848
B18: Revenue - products | C18: =255887+318898 -> 574785 | D18: =272311+365648 -> 637959 | E18: =296266+420658 -> 716924 | F18: =E18*(1+F39) -> 805056.43 | G18: =F18*(1+G39) -> 895555.18 | H18: =G18*(1+H39) -> 1009191.8 | I18: =H18*(1+I39) -> 1137247.8 | J18: =I18*(1+J39) -> 1281552.7
B19: Cost of Sales | C19: =-304739-90619 -> -395358 | D19: =-326288-98505 -> -424793 | E19: =-356414-109074 -> -465488 | F19: =F20-F18 -> -522481.62 | G19: =G20-G18 -> -573155.32 | H19: =H20-H18 -> -635790.85 | I19: =I20-I18 -> -716466.09 | J19: =J20-J18 -> -807378.19
B20: Gross Profit | C20: =SUM(C18:C19) -> 179427 | D20: =SUM(D18:D19) -> 213166 | E20: =SUM(E18:E19) -> 251436 | F20: =F18*F40 -> 282574.81 | G20: =G18*G40 -> 322399.86 | H20: =H18*H40 -> 373400.97 | I20: =I18*I40 -> 420781.67 | J20: =J18*J40 -> 474174.49
B21: Selling, general & administrative | C21: =-44370-11816 -> -56186 | D21: =-43907-11359 -> -55266 | E21: =-47129-11172 -> -58301 | F21: =-F18*F42 -> -61141 | G21: =-G18*G42 -> -66853 | H21: =-H18*H42 -> -66853 | I21: =-I18*I42 -> -75335.95 | J21: =-J18*J42 -> -84895.299
B22: R&D: Technology and Infrastructure | C22: -85622 | D22: -88544 | E22: -108521 | F22: =F18*F41*-1 -> -120758.46 | G22: =G18*G41*-1 -> -138811.05 | H22: =H18*H41*-1 -> -158443.12 | I22: =I18*I41*-1 -> -178547.9 | J22: =J18*J41*-1 -> -201203.77
B23: Other operating expense, net | C23: -767 | D23: -763 | E23: -4639 | F23: =$D$23 -> -763 | G23: =$D$23 -> -763 | H23: =$D$23 -> -763 | I23: =$D$23 -> -763 | J23: =$D$23 -> -763
B24: Operating profit (EBIT) | C24: =SUM(C20:C23) -> 36852 | D24: =SUM(D20:D23) -> 68593 | E24: =SUM(E20:E23) -> 79975 | F24: =SUM(F20:F23) -> 99912.342 | G24: =SUM(G20:G23) -> 115972.81 | H24: =SUM(H20:H23) -> 147341.86 | I24: =SUM(I20:I23) -> 166134.82 | J24: =SUM(J20:J23) -> 187312.42
B25: Interest income | C25: 2949 | D25: 4677 | E25: 4381 | F25: =F138 -> 3512.4978 | G25: =G138 -> 3399.5168 | H25: =H138 -> 3823.678 | I25: =I138 -> 4665.8363 | J25: =J138 -> 5755.9661
B26: Interest expense | C26: -3182 | D26: -2406 | E26: -2274 | F26: =F134 -> -2524.4321 | G26: =G134 -> -2524.4321 | H26: =H134 -> -2524.4321 | I26: =I134 -> -2524.4321 | J26: =J134 -> -2524.4321
B27: Other expense, net | C27: 938 | D27: -2250 | E27: 15229 | F27: =E27 -> 15229 | G27: =F27 -> 15229 | H27: =G27 -> 15229 | I27: =H27 -> 15229 | J27: =I27 -> 15229
B28: Pretax profit | C28: =SUM(C24:C27) -> 37557 | D28: =SUM(D24:D27) -> 68614 | E28: =SUM(E24:E27) -> 97311 | F28: =SUM(F24:F27) -> 116129.41 | G28: =SUM(G24:G27) -> 132076.9 | H28: =SUM(H24:H27) -> 163870.1 | I28: =SUM(I24:I27) -> 183505.23 | J28: =SUM(J24:J27) -> 205772.96
B29: Taxes | C29: -7120 | D29: -9265 | E29: -19087 | F29: =-F43*F28 -> -21530.392 | G29: =-G43*G28 -> -24764.418 | H29: =-H43*H28 -> -30479.839 | I29: =-I43*I28 -> -34131.972 | J29: =-J43*J28 -> -38273.77
B30: Equity method investment, net of tax | C30: -12 | D30: -101 | E30: -554
B31: Net income | C31: =SUM(C28:C30) -> 30425 | D31: =SUM(D28:D30) -> 59248 | E31: =SUM(E28:E30) -> 77670 | F31: =SUM(F28:F30) -> 94599.016 | G31: =SUM(G28:G30) -> 107312.48 | H31: =SUM(H28:H30) -> 133390.26 | I31: =SUM(I28:I30) -> 149373.26 | J31: =SUM(J28:J30) -> 167499.19
B33: Depreciation & amortization | C33: 48663 | D33: 52795 | E33: 65756 | F33: =F109 -> 86990.258 | G33: =G109 -> 94008.777 | H33: =H109 -> 107411.25 | I33: =I109 -> 125444.27 | J33: =J109 -> 146324.26
B34: EBITDA | C34: =C24+C33 -> 85515 | D34: =D24+D33 -> 121388 | E34: =E24+E33 -> 145731 | F34: =F24+F33 -> 186902.6 | G34: =G24+G33 -> 209981.59 | H34: =H24+H33 -> 254753.1 | I34: =I24+I33 -> 291579.09 | J34: =J24+J33 -> 333636.68
B35: Stock based compensation | C35: 24023 | D35: 22011 | E35: 19467 | F35: =E35*(1+F39) -> 21860.104 | G35: =F35*(1+G39) -> 24317.463 | H35: =G35*(1+H39) -> 27403.096 | I35: =H35*(1+I39) -> 30880.264 | J35: =I35*(1+J39) -> 34798.648
B36: Adjusted EBITDA | C36: =SUM(C34:C35) -> 109538 | D36: =SUM(D34:D35) -> 143399 | E36: =SUM(E34:E35) -> 165198 | F36: =SUM(F34:F35) -> 208762.7 | G36: =SUM(G34:G35) -> 234299.05 | H36: =SUM(H34:H35) -> 282156.2 | I36: =SUM(I34:I35) -> 322459.35 | J36: =SUM(J34:J35) -> 368435.33
B38: Growth rates & margins
B39: Revenue growth | D39: =D18/C18-1 -> 0.10990892 | E39: =E18/D18-1 -> 0.12377755 | F39: =F156 -> 0.12293134 | G39: =G156 -> 0.11241293 | H39: =H156 -> 0.1268896 | I39: =I156 -> 0.1268896 | J39: =J156 -> 0.1268896
B40: Gross profit margin | C40: =C20/C18 -> 0.31216368 | D40: =D20/D18 -> 0.33413746 | E40: =E20/E18 -> 0.350715 | F40: =F157 -> 0.351 | G40: =G157 -> 0.36 | H40: =H157 -> 0.37 | I40: =I157 -> 0.37 | J40: =J157 -> 0.37
B41: R&D % of sales | C41: =C22/C18*-1 -> 0.14896353 | D41: =D22/D18*-1 -> 0.13879262 | E41: =E22/E18*-1 -> 0.1513703 | F41: =F171 -> 0.15 | G41: =G171 -> 0.155 | H41: =H171 -> 0.157 | I41: =I171 -> 0.157 | J41: =J171 -> 0.157
B42: SG&A % of sales | C42: =C21/C18*-1 -> 0.097751333 | D42: =D21/D18*-1 -> 0.086629392 | E42: =E21/E18*-1 -> 0.081321033 | F42: =F159 -> 0.075946229 | G42: =G159 -> 0.074649783 | H42: =H159 -> 0.066244096 | I42: =I159 -> 0.066244096 | J42: =J159 -> 0.066244096
B43: Tax rate | C43: =-C29/C28 -> 0.18957851 | D43: =-D29/D28 -> 0.13503075 | E43: =-E29/E28 -> 0.19614432 | F43: 0.1854 | G43: 0.1875 | H43: 0.186 | I43: =H43 -> 0.186 | J43: =I43 -> 0.186
B45: BALANCE SHEET
B46: =B15 -> Fiscal year | D46: =D15 -> 2024 | E46: =E15 -> 2025 | F46: =F15 -> 2026 | G46: =G15 -> 2027 | H46: =H15 -> 2028 | I46: =I15 -> 2029 | J46: =J15 -> 2030
B47: =B16 -> Fiscal year end date | D47: =D16 -> 45657 | E47: =E16 -> 46022 | F47: =F16 -> 46387 | G47: =G16 -> 46752 | H47: =H16 -> 47118 | I47: =I16 -> 47483 | J47: =J16 -> 47848
B48: Cash & equivalents, ST and LT marketable securities | D48: =78779+22423 -> 101202 | E48: =86810+36219 -> 123029 | F48: =F93+E48 -> 111137.52 | G48: =G93+F48 -> 115496.93 | H48: =H93+G48 -> 139414.94 | I48: =I93+H48 -> 171640.81 | J48: =J93+I48 -> 212090.26
B49: Accounts receivable | D49: 55451 | E49: 67729 | F49: =E49*(1+F39) -> 76055.017 | G49: =F49*(1+G39) -> 84604.584 | H49: =G49*(1+H39) -> 95340.026 | I49: =H49*(1+I39) -> 107437.68 | J49: =I49*(1+J39) -> 121070.41
B50: Inventories | D50: 34214 | E50: 38325 | F50: =E50*F19/E19 -> 43017.453 | G50: =F50*G19/F19 -> 47189.568 | H50: =G50*H19/G19 -> 52346.536 | I50: =H50*I19/H19 -> 58988.767 | J50: =I50*J19/I19 -> 66473.828
B51: Property, plant & equipment | D51: 252665 | E51: 357025 | F51: =F102 -> 475008.41 | G51: =G102 -> 590223.81 | H51: =H102 -> 711783.4 | I51: =I102 -> 844364 | J51: =J102 -> 988805.28
B52: Other non current assets | D52: =76141+23074+82147 -> 181362 | E52: =86054+23273+122607 -> 231934 | F52: =E52*(1+F39) -> 260445.96 | G52: =F52*(1+G39) -> 289723.45 | H52: =G52*(1+H39) -> 326486.34 | I52: =H52*(1+I39) -> 367914.06 | J52: =I52*(1+J39) -> 414598.53
B53: Total assets | D53: =SUM(D48:D52) -> 624894 | E53: =SUM(E48:E52) -> 818042 | F53: =SUM(F48:F52) -> 965664.36 | G53: =SUM(G48:G52) -> 1127238.3 | H53: =SUM(H48:H52) -> 1325371.2 | I53: =SUM(I48:I52) -> 1550345.3 | J53: =SUM(J48:J52) -> 1803038.3
B55: Accounts payable | D55: 94363 | E55: 121909 | F55: =E55*F19/E19 -> 136835.35 | G55: =F55*G19/F19 -> 150106.54 | H55: =G55*H19/G19 -> 166510.47 | I55: =H55*I19/H19 -> 187638.92 | J55: =I55*J19/I19 -> 211448.35
B56: Other current liabilities | D56: 66965 | E56: 75520 | F56: =E56*(1+F39) -> 84803.775 | G56: =F56*(1+G39) -> 94336.816 | H56: =G56*(1+H39) -> 106307.18 | I56: =H56*(1+I39) -> 119796.45 | J56: =I56*(1+J39) -> 134997.38
B57: Deferred revenue (current) | D57: 18103 | E57: 20576 | F57: =E57*(1+F39) -> 23105.435 | G57: =F57*(1+G39) -> 25702.785 | H57: =G57*(1+H39) -> 28964.201 | I57: =H57*(1+I39) -> 32639.457 | J57: =I57*(1+J39) -> 36781.065
B58: Long term lease liabilities | D58: 78277 | E58: 87339 | F58: =E58 -> 87339 | G58: =F58 -> 87339 | H58: =G58 -> 87339 | I58: =H58 -> 87339 | J58: =I58 -> 87339
B59: Long term debt (includes current portion) | D59: 52623 | E59: 65648 | F59: =E59 -> 65648 | G59: =F59 -> 65648 | H59: =G59 -> 65648 | I59: =H59 -> 65648 | J59: =I59 -> 65648
B60: Other non current liabilities | D60: 28593 | E60: 35985 | F60: =E60*(1+F39) -> 40408.684 | G60: =F60*(1+G39) -> 44951.143 | H60: =G60*(1+H39) -> 50654.975 | I60: =H60*(1+I39) -> 57082.565 | J60: =I60*(1+J39) -> 64325.749
B61: Total liabilities | D61: =SUM(D55:D60) -> 338924 | E61: =SUM(E55:E60) -> 406977 | F61: =SUM(F55:F60) -> 438140.24 | G61: =SUM(G55:G60) -> 468084.28 | H61: =SUM(H55:H60) -> 505423.82 | I61: =SUM(I55:I60) -> 550144.39 | J61: =SUM(J55:J60) -> 600539.53
B63: Common stock | D63: 111 | E63: 112 | F63: =E63 -> 112 | G63: =F63 -> 112 | H63: =G63 -> 112 | I63: =H63 -> 112 | J63: =I63 -> 112
B64: Treasury stock | D64: -7837 | E64: -7837 | F64: =E64 -> -7837 | G64: =F64 -> -7837 | H64: =G64 -> -7837 | I64: =H64 -> -7837 | J64: =I64 -> -7837
B65: APIC | D65: 120864 | E65: 140024 | F65: =E65++F35 -> 161884.1 | G65: =F65++G35 -> 186201.57 | H65: =G65++H35 -> 213604.66 | I65: =H65++I35 -> 244484.93 | J65: =I65++J35 -> 279283.57
B66: Retained earnings | D66: 172866 | E66: 250536 | F66: =F122 -> 345135.02 | G66: =G122 -> 452447.49 | H66: =H122 -> 585837.76 | I66: =I122 -> 735211.01 | J66: =J122 -> 902710.2
B67: Other comprehensive income | D67: -34 | E67: 28230 | F67: =E67 -> 28230 | G67: =F67 -> 28230 | H67: =G67 -> 28230 | I67: =H67 -> 28230 | J67: =I67 -> 28230
B68: Total equity | D68: =SUM(D63:D67) -> 285970 | E68: =SUM(E63:E67) -> 411065 | F68: =SUM(F63:F67) -> 527524.12 | G68: =SUM(G63:G67) -> 659154.06 | H68: =SUM(H63:H67) -> 819947.42 | I68: =SUM(I63:I67) -> 1000200.9 | J68: =SUM(J63:J67) -> 1202498.8
B70: Balance check | D70: =ROUND(D53-D61-D68,3) -> 0 | E70: =ROUND(E53-E61-E68,3) -> 0 | F70: =ROUND(F53-F61-F68,3) -> 0 | G70: =ROUND(G53-G61-G68,3) -> 0 | H70: =ROUND(H53-H61-H68,3) -> 0 | I70: =ROUND(I53-I61-I68,3) -> 0 | J70: =ROUND(J53-J61-J68,3) -> 0
B72: CASH FLOW STATEMENT
B73: =B15 -> Fiscal year | F73: =F15 -> 2026 | G73: =G15 -> 2027 | H73: =H15 -> 2028 | I73: =I15 -> 2029 | J73: =J15 -> 2030
B74: =B16 -> Fiscal year end date | F74: =F16 -> 46387 | G74: =G16 -> 46752 | H74: =H16 -> 47118 | I74: =I16 -> 47483 | J74: =J16 -> 47848
B76: Net income | F76: =F31 -> 94599.016 | G76: =G31 -> 107312.48 | H76: =H31 -> 133390.26 | I76: =I31 -> 149373.26 | J76: =J31 -> 167499.19
B77: Depreciation and amortization | F77: =F33 -> 86990.258 | G77: =G33 -> 94008.777 | H77: =H33 -> 107411.25 | I77: =I33 -> 125444.27 | J77: =J33 -> 146324.26
B78: Stock based compensation | F78: =F35 -> 21860.104 | G78: =G35 -> 24317.463 | H78: =H35 -> 27403.096 | I78: =I35 -> 30880.264 | J78: =J35 -> 34798.648
B79: Decreases / (Increases) in working capital assets | F79: =-1*(SUM(F49:F50)-SUM(E49:E50)) -> -13018.47 | G79: =-1*(SUM(G49:G50)-SUM(F49:F50)) -> -12721.682 | H79: =-1*(SUM(H49:H50)-SUM(G49:G50)) -> -15892.41 | I79: =-1*(SUM(I49:I50)-SUM(H49:H50)) -> -18739.889 | J79: =-1*(SUM(J49:J50)-SUM(I49:I50)) -> -21117.786
B80: Increases / (Decreases) in working capital liabilities | F80: =SUM(F55:F57)-SUM(E55:E57) -> 26739.557 | G80: =SUM(G55:G57)-SUM(F55:F57) -> 25401.58 | H80: =SUM(H55:H57)-SUM(G55:G57) -> 31635.712 | I80: =SUM(I55:I57)-SUM(H55:H57) -> 38292.978 | J80: =SUM(J55:J57)-SUM(I55:I57) -> 43151.959
B81: Other non current assets | F81: =-(F114) -> -55300.607 | G81: =-(G114) -> -59077.534 | H81: =-(H114) -> -70344.249 | I81: =-(I114) -> -79270.202 | J81: =-(J114) -> -89328.767
B82: Other non current liabilities | F82: =F60-E60 -> 4423.6843 | G82: =G60-F60 -> 4542.4586 | H82: =H60-G60 -> 5703.8325 | I82: =I60-H60 -> 6427.5896 | J82: =J60-I60 -> 7243.1838
B83: Cash from operating activities | F83: =SUM(F76:F82) -> 166293.54 | G83: =SUM(G76:G82) -> 183783.54 | H83: =SUM(H76:H82) -> 219307.49 | I83: =SUM(I76:I82) -> 252408.26 | J83: =SUM(J76:J82) -> 288570.69
B85: Capital expenditures | F85: =-(F100) -> -178185.02 | G85: =-(G100) -> -179424.13 | H85: =-(H100) -> -195389.49 | I85: =-(I100) -> -220182.38 | J85: =-(J100) -> -248121.24
B86: Cash from investing activities | F86: =IFERROR(F85,"NA") -> -178185.02 | G86: =IFERROR(G85,"NA") -> -179424.13 | H86: =IFERROR(H85,"NA") -> -195389.49 | I86: =IFERROR(I85,"NA") -> -220182.38 | J86: =IFERROR(J85,"NA") -> -248121.24
B88: Long term debt | F88: =F59-E59 -> 0 | G88: =G59-F59 -> 0 | H88: =H59-G59 -> 0 | I88: =I59-H59 -> 0 | J88: =J59-I59 -> 0
B89: Share repurchases | F89: =F121 -> 0 | G89: =G121 -> 0 | H89: =H121 -> 0 | I89: =I121 -> 0 | J89: =J121 -> 0
B90: Common dividends | F90: =F120 -> 0 | G90: =G120 -> 0 | H90: =H120 -> 0 | I90: =I120 -> 0 | J90: =J120 -> 0
B91: Cash from financing activities | F91: =SUM(F88:F90) -> 0 | G91: =SUM(G88:G90) -> 0 | H91: =SUM(H88:H90) -> 0 | I91: =SUM(I88:I90) -> 0 | J91: =SUM(J88:J90) -> 0
B93: Net change in cash during period | F93: =F83+F86+F91 -> -11891.478 | G93: =G83+G86+G91 -> 4359.4108 | H93: =H83+H86+H91 -> 23918.003 | I93: =I83+I86+I91 -> 32225.877 | J93: =J83+J86+J91 -> 40449.448
B95: PROPERTY, PLANT & EQUIPMENT
B96: =B15 -> Fiscal year | C96: =C15 -> 2023 | D96: =D15 -> 2024 | E96: =E15 -> 2025 | F96: =F15 -> 2026 | G96: =G15 -> 2027 | H96: =H15 -> 2028 | I96: =I15 -> 2029 | J96: =J15 -> 2030
B97: =B16 -> Fiscal year end date | C97: =C16 -> 45291 | D97: =D16 -> 45657 | E97: =E16 -> 46022 | F97: =F16 -> 46387 | G97: =G16 -> 46752 | H97: =H16 -> 47118 | I97: =I16 -> 47483 | J97: =J16 -> 47848
F98: Forecast
B99: Beginning of period | F99: =E102 -> 357025 | G99: =F102 -> 475008.41 | H99: =G102 -> 590223.81 | I99: =H102 -> 711783.4 | J99: =I102 -> 844364
B100: Plus: Capital expenditures | C100: 52729 | D100: 82999 | E100: 131819 | F100: 178185.02 | G100: 179424.13 | H100: 195389.49 | I100: =H100*(1+I39) -> 220182.38 | J100: =I100*(1+J39) -> 248121.24
B101: Less: Depreciation | C101: -30200 | D101: -32100 | E101: -41900 | F101: =-(F104*F100) -> -60201.608 | G101: =-(G104*G100) -> -64208.736 | H101: =-(H104*H100) -> -73829.891 | I101: =-(I104*I100) -> -87601.785 | J101: =-(J104*J100) -> -103679.96
B102: End of period | D102: =D51 -> 252665 | E102: =E51 -> 357025 | F102: =SUM(F99:F101) -> 475008.41 | G102: =SUM(G99:G101) -> 590223.81 | H102: =SUM(H99:H101) -> 711783.4 | I102: =SUM(I99:I101) -> 844364 | J102: =SUM(J99:J101) -> 988805.28
L103: Step
B104: D&A related to PP&E as a % of capex | C104: =-(C101/C100) -> 0.57273986 | D104: =-(D101/D100) -> 0.38675165 | E104: =-(E101/E100) -> 0.3178601 | F104: =E104+$L$104 -> 0.3378601 | G104: =F104+$L$104 -> 0.3578601 | H104: =G104+$L$104 -> 0.3778601 | I104: =H104+$L$104 -> 0.3978601 | J104: =I104+$L$104 -> 0.4178601 | L104: 0.02
B106: IMPUTING TOTAL DEPRECIATION & AMORTIZATION
B107: D&A not related to PP&E | C107: =C109+C101 -> 18463 | D107: =D109+D101 -> 20695 | E107: =E109+E101 -> 23856 | F107: =F108*F18 -> 26788.65 | G107: =G108*G18 -> 29800.041 | H107: =H108*H18 -> 33581.356 | I107: =I108*I18 -> 37842.481 | J107: =J108*J18 -> 42644.298
B108: as % of revenue | C108: =C107/C18 -> 0.032121576 | D108: =D107/D18 -> 0.032439389 | E108: =E107/E18 -> 0.033275494 | F108: =E108 -> 0.033275494 | G108: =F108 -> 0.033275494 | H108: =G108 -> 0.033275494 | I108: =H108 -> 0.033275494 | J108: =I108 -> 0.033275494
B109: Depreciation & Amortization - Total | C109: =C33 -> 48663 | D109: =D33 -> 52795 | E109: =E33 -> 65756 | F109: =-F101+F107 -> 86990.258 | G109: =-G101+G107 -> 94008.777 | H109: =-H101+H107 -> 107411.25 | I109: =-I101+I107 -> 125444.27 | J109: =-J101+J107 -> 146324.26
B111: OTHER NON-CURRENT ASSETS
B112: Beginning of period | F112: =E115 -> 231934 | G112: =F115 -> 260445.96 | H112: =G115 -> 289723.45 | I112: =H115 -> 326486.34 | J112: =I115 -> 367914.06
B113: Less: Amortization of intangible assets | F113: =-(F107) -> -26788.65 | G113: =-(G107) -> -29800.041 | H113: =-(H107) -> -33581.356 | I113: =-(I107) -> -37842.481 | J113: =-(J107) -> -42644.298
B114: Plus: Additions | F114: =F115-F113-F112 -> 55300.607 | G114: =G115-G113-G112 -> 59077.534 | H114: =H115-H113-H112 -> 70344.249 | I114: =I115-I113-I112 -> 79270.202 | J114: =J115-J113-J112 -> 89328.767
B115: End of period | D115: =D52 -> 181362 | E115: =E52 -> 231934 | F115: =F52 -> 260445.96 | G115: =G52 -> 289723.45 | H115: =H52 -> 326486.34 | I115: =I52 -> 367914.06 | J115: =J52 -> 414598.53
B117: RETAINED EARNINGS
B118: Beginning of period | F118: =E122 -> 250536 | G118: =F122 -> 345135.02 | H118: =G122 -> 452447.49 | I118: =H122 -> 585837.76 | J118: =I122 -> 735211.01
B119: Plus: Net income | C119: =C31 -> 30425 | D119: =D31 -> 59248 | E119: =E31 -> 77670 | F119: =F31 -> 94599.016 | G119: =G31 -> 107312.48 | H119: =H31 -> 133390.26 | I119: =I31 -> 149373.26 | J119: =J31 -> 167499.19
...
